second_module/__init__.py
second_module/second.py
second_module-0.5.dist-info/METADATA
second_module-0.5.dist-info/WHEEL
second_module-0.5.dist-info/top_level.txt
second_module-0.5.dist-info/RECORD
