Metadata-Version: 2.1
Name: second-module
Version: 0.5
Summary: My second module for practice
Home-page: UNKNOWN
Author: UNKNOWN
Author-email: UNKNOWN
License: UNKNOWN
Platform: UNKNOWN
